{
    "size":[
        1000.000015,
        100.000001,
        1000.000015
    ],
    "walls":[
        
    ],
    "lights":[
        {
            "color":[
                0.75,
                0.74,
                0.72
            ],
            "pos":[
                487.300007,
                54.000001,
                6
            ]
        }
    ],
    "interior":{
        "material":"Terrain/UnderwaterCeiling",
        "color":[
            
        ],
        "height":90.000001
    },
    "gates":[
        {
            "dest_vec":[
                138.400002,
                57.600001,
                180.500003
            ],
            "dest_map":"Serpent's Pass",
            "material":"GateMatWhite",
            "pos":[
                487.300007,
                54.000001,
                2.5
            ]
        }
    ],
    "water_planes":[
        {
            "is_solid":false,
            "material":"Terrain/LargeWater",
            "scale":[
                2.5,
                2.5
            ],
            "sound":"",
            "pos":[
                500.000007,
                52.000001,
                500.000007
            ]
        }
    ],
    "portals":[
        
    ],
    "billboards":[
        {
            "material":"CaveLight",
            "scale":[
                10,
                10
            ],
            "pos":[
                487.300007,
                54.000001,
                6
            ]
        }
    ],
    "material":"Terrain/HydroPillar",
    "heightmap":"lastCaveterrain.png",
    "collision_shapes":[
        
    ],
    "particles":[
        
    ],
    "weather":"None",
    "music":[
        
    ],
    "spawn_pos":[
        487.300007,
        14,
        0.1
    ],
    "random_objects":[
        
    ],
    "objects":[
        
    ]
}